{
  "buildType": "perf",
  "compiler": "ldc2 1.42.0",
  "host": "fedora",
  "meshType": "grid",
  "n": 316,
  "faceCount": 99856,
  "viewport": "1280x960",
  "repeats": 5,
  "cases": [
    {
      "name": "move/baseline",
      "kernelMedianUs": 13791.200,
      "kernelP95Us": 14081.700,
      "pipeMedianUs": 7171.300,
      "dominantStage": "kernelApply",
      "vertsTouched": 2009780
    },
    {
      "name": "move/falloff=linear",
      "kernelMedianUs": 26424.100,
      "kernelP95Us": 26469.800,
      "pipeMedianUs": 4234.100,
      "dominantStage": "kernelApply",
      "vertsTouched": 2009780
    },
    {
      "name": "move/falloff=radial",
      "kernelMedianUs": 25112.800,
      "kernelP95Us": 25197.900,
      "pipeMedianUs": 4706.200,
      "dominantStage": "kernelApply",
      "vertsTouched": 2009780
    },
    {
      "name": "move/falloff=element",
      "kernelMedianUs": 0.600,
      "kernelP95Us": 0.700,
      "pipeMedianUs": 60.200,
      "dominantStage": "cacheInvalidate",
      "vertsTouched": 20
    },
    {
      "name": "move/falloff=screen",
      "kernelMedianUs": 50500.700,
      "kernelP95Us": 50698.100,
      "pipeMedianUs": 4474.400,
      "dominantStage": "kernelApply",
      "vertsTouched": 2009780
    },
    {
      "name": "move/falloff=cylinder",
      "kernelMedianUs": 36421.000,
      "kernelP95Us": 36581.400,
      "pipeMedianUs": 8349.200,
      "dominantStage": "kernelApply",
      "vertsTouched": 2009780
    },
    {
      "name": "move/falloff=selection",
      "kernelMedianUs": 7644.500,
      "kernelP95Us": 7705.900,
      "pipeMedianUs": 11235.300,
      "dominantStage": "kernelApply",
      "vertsTouched": 1001720
    },
    {
      "name": "move/symmetry=X",
      "kernelMedianUs": 20238.700,
      "kernelP95Us": 20317.000,
      "pipeMedianUs": 8077.800,
      "dominantStage": "kernelApply",
      "vertsTouched": 2009780
    },
    {
      "name": "move/acen=selection",
      "kernelMedianUs": 6814.600,
      "kernelP95Us": 6870.100,
      "pipeMedianUs": 2894.200,
      "dominantStage": "kernelApply",
      "vertsTouched": 1001720
    },
    {
      "name": "move/acen=local",
      "kernelMedianUs": 6590.300,
      "kernelP95Us": 6638.900,
      "pipeMedianUs": 13998.300,
      "dominantStage": "pipeAcen",
      "vertsTouched": 1001720
    },
    {
      "name": "move/snap=grid",
      "kernelMedianUs": 13487.300,
      "kernelP95Us": 13881.900,
      "pipeMedianUs": 7637.400,
      "dominantStage": "kernelApply",
      "vertsTouched": 2009780
    },
    {
      "name": "move/snap=vertex",
      "kernelMedianUs": 13382.000,
      "kernelP95Us": 13621.000,
      "pipeMedianUs": 5999.200,
      "dominantStage": "kernelApply",
      "vertsTouched": 2009780
    },
    {
      "name": "move/snap=edge",
      "kernelMedianUs": 13715.600,
      "kernelP95Us": 13798.700,
      "pipeMedianUs": 5688.400,
      "dominantStage": "kernelApply",
      "vertsTouched": 2009780
    },
    {
      "name": "move/snap=edgeCenter",
      "kernelMedianUs": 13316.600,
      "kernelP95Us": 13634.200,
      "pipeMedianUs": 6047.500,
      "dominantStage": "kernelApply",
      "vertsTouched": 2009780
    },
    {
      "name": "move/snap=polygon",
      "kernelMedianUs": 13330.600,
      "kernelP95Us": 13822.500,
      "pipeMedianUs": 6179.700,
      "dominantStage": "kernelApply",
      "vertsTouched": 2009780
    },
    {
      "name": "move/snap=polyCenter",
      "kernelMedianUs": 13313.700,
      "kernelP95Us": 13406.000,
      "pipeMedianUs": 5653.000,
      "dominantStage": "kernelApply",
      "vertsTouched": 2009780
    },
    {
      "name": "move/snap=workplane",
      "kernelMedianUs": 13608.300,
      "kernelP95Us": 13845.400,
      "pipeMedianUs": 7510.700,
      "dominantStage": "kernelApply",
      "vertsTouched": 2009780
    },
    {
      "name": "move/selection=single",
      "kernelMedianUs": 0.300,
      "kernelP95Us": 0.500,
      "pipeMedianUs": 4759.200,
      "dominantStage": "pipeAcen",
      "vertsTouched": 20
    },
    {
      "name": "move/selection=ring",
      "kernelMedianUs": 42.000,
      "kernelP95Us": 42.400,
      "pipeMedianUs": 4655.700,
      "dominantStage": "pipeAcen",
      "vertsTouched": 6340
    },
    {
      "name": "move/selection=half",
      "kernelMedianUs": 6606.600,
      "kernelP95Us": 6614.800,
      "pipeMedianUs": 2864.500,
      "dominantStage": "kernelApply",
      "vertsTouched": 1001720
    },
    {
      "name": "rotate/baseline",
      "kernelMedianUs": 13260.500,
      "kernelP95Us": 13296.900,
      "pipeMedianUs": 6920.900,
      "dominantStage": "kernelApply",
      "vertsTouched": 2009780
    },
    {
      "name": "rotate/falloff=linear",
      "kernelMedianUs": 26556.900,
      "kernelP95Us": 26622.600,
      "pipeMedianUs": 3964.200,
      "dominantStage": "kernelApply",
      "vertsTouched": 2009780
    },
    {
      "name": "rotate/falloff=radial",
      "kernelMedianUs": 25181.000,
      "kernelP95Us": 25310.400,
      "pipeMedianUs": 4280.700,
      "dominantStage": "kernelApply",
      "vertsTouched": 2009780
    },
    {
      "name": "rotate/falloff=element",
      "kernelMedianUs": 0.600,
      "kernelP95Us": 0.700,
      "pipeMedianUs": 61.100,
      "dominantStage": "cacheInvalidate",
      "vertsTouched": 20
    },
    {
      "name": "rotate/falloff=screen",
      "kernelMedianUs": 49519.200,
      "kernelP95Us": 49533.600,
      "pipeMedianUs": 4595.900,
      "dominantStage": "kernelApply",
      "vertsTouched": 2009780
    },
    {
      "name": "rotate/falloff=cylinder",
      "kernelMedianUs": 36473.500,
      "kernelP95Us": 36568.100,
      "pipeMedianUs": 7396.700,
      "dominantStage": "kernelApply",
      "vertsTouched": 2009780
    },
    {
      "name": "rotate/falloff=selection",
      "kernelMedianUs": 7626.600,
      "kernelP95Us": 7643.700,
      "pipeMedianUs": 11203.200,
      "dominantStage": "kernelApply",
      "vertsTouched": 1001720
    },
    {
      "name": "rotate/symmetry=X",
      "kernelMedianUs": 20262.400,
      "kernelP95Us": 20294.100,
      "pipeMedianUs": 7997.900,
      "dominantStage": "kernelApply",
      "vertsTouched": 2009780
    },
    {
      "name": "rotate/acen=selection",
      "kernelMedianUs": 6622.700,
      "kernelP95Us": 6626.800,
      "pipeMedianUs": 2851.300,
      "dominantStage": "kernelApply",
      "vertsTouched": 1001720
    },
    {
      "name": "rotate/acen=local",
      "kernelMedianUs": 6615.800,
      "kernelP95Us": 6732.900,
      "pipeMedianUs": 13854.900,
      "dominantStage": "pipeAcen",
      "vertsTouched": 1001720
    },
    {
      "name": "rotate/selection=single",
      "kernelMedianUs": 0.300,
      "kernelP95Us": 0.300,
      "pipeMedianUs": 4145.000,
      "dominantStage": "pipeAcen",
      "vertsTouched": 20
    },
    {
      "name": "rotate/selection=ring",
      "kernelMedianUs": 41.700,
      "kernelP95Us": 41.700,
      "pipeMedianUs": 4028.000,
      "dominantStage": "pipeAcen",
      "vertsTouched": 6340
    },
    {
      "name": "rotate/selection=half",
      "kernelMedianUs": 6607.000,
      "kernelP95Us": 6608.500,
      "pipeMedianUs": 2776.100,
      "dominantStage": "kernelApply",
      "vertsTouched": 1001720
    },
    {
      "name": "scale/baseline",
      "kernelMedianUs": 13363.900,
      "kernelP95Us": 13377.200,
      "pipeMedianUs": 7143.900,
      "dominantStage": "kernelApply",
      "vertsTouched": 2009780
    },
    {
      "name": "scale/falloff=linear",
      "kernelMedianUs": 26451.600,
      "kernelP95Us": 26467.200,
      "pipeMedianUs": 3933.400,
      "dominantStage": "kernelApply",
      "vertsTouched": 2009780
    },
    {
      "name": "scale/falloff=radial",
      "kernelMedianUs": 24951.600,
      "kernelP95Us": 24964.700,
      "pipeMedianUs": 4374.400,
      "dominantStage": "kernelApply",
      "vertsTouched": 2009780
    },
    {
      "name": "scale/falloff=element",
      "kernelMedianUs": 0.500,
      "kernelP95Us": 0.500,
      "pipeMedianUs": 58.900,
      "dominantStage": "cacheInvalidate",
      "vertsTouched": 20
    },
    {
      "name": "scale/falloff=screen",
      "kernelMedianUs": 50174.200,
      "kernelP95Us": 50428.200,
      "pipeMedianUs": 4005.400,
      "dominantStage": "kernelApply",
      "vertsTouched": 2009780
    },
    {
      "name": "scale/falloff=cylinder",
      "kernelMedianUs": 36454.800,
      "kernelP95Us": 37055.600,
      "pipeMedianUs": 7540.100,
      "dominantStage": "kernelApply",
      "vertsTouched": 2009780
    },
    {
      "name": "scale/falloff=selection",
      "kernelMedianUs": 7706.900,
      "kernelP95Us": 7711.800,
      "pipeMedianUs": 11191.400,
      "dominantStage": "kernelApply",
      "vertsTouched": 1001720
    },
    {
      "name": "scale/symmetry=X",
      "kernelMedianUs": 20303.100,
      "kernelP95Us": 20378.300,
      "pipeMedianUs": 7780.600,
      "dominantStage": "kernelApply",
      "vertsTouched": 2009780
    },
    {
      "name": "scale/acen=selection",
      "kernelMedianUs": 6606.300,
      "kernelP95Us": 6609.500,
      "pipeMedianUs": 2808.700,
      "dominantStage": "kernelApply",
      "vertsTouched": 1001720
    },
    {
      "name": "scale/acen=local",
      "kernelMedianUs": 6720.400,
      "kernelP95Us": 6776.400,
      "pipeMedianUs": 13935.800,
      "dominantStage": "pipeAcen",
      "vertsTouched": 1001720
    },
    {
      "name": "scale/selection=single",
      "kernelMedianUs": 0.300,
      "kernelP95Us": 0.300,
      "pipeMedianUs": 4270.100,
      "dominantStage": "pipeAcen",
      "vertsTouched": 20
    },
    {
      "name": "scale/selection=ring",
      "kernelMedianUs": 42.300,
      "kernelP95Us": 42.400,
      "pipeMedianUs": 4135.900,
      "dominantStage": "pipeAcen",
      "vertsTouched": 6340
    },
    {
      "name": "scale/selection=half",
      "kernelMedianUs": 6614.400,
      "kernelP95Us": 6629.200,
      "pipeMedianUs": 2794.800,
      "dominantStage": "kernelApply",
      "vertsTouched": 1001720
    },
    {
      "name": "delete/vertices/whole",
      "kernelMedianUs": 13202.500,
      "kernelP95Us": 13407.600,
      "pipeMedianUs": null,
      "dominantStage": "commandApply",
      "vertsTouched": 0
    },
    {
      "name": "delete/vertices/half",
      "kernelMedianUs": 1608688.800,
      "kernelP95Us": 1627914.600,
      "pipeMedianUs": null,
      "dominantStage": "commandApply",
      "vertsTouched": 0
    },
    {
      "name": "delete/edges/whole",
      "kernelMedianUs": 63035.700,
      "kernelP95Us": 63059.100,
      "pipeMedianUs": null,
      "dominantStage": "commandApply",
      "vertsTouched": 0
    },
    {
      "name": "delete/polygons/whole",
      "kernelMedianUs": 12609.100,
      "kernelP95Us": 12937.400,
      "pipeMedianUs": null,
      "dominantStage": "commandApply",
      "vertsTouched": 0
    },
    {
      "name": "delete/polygons/half",
      "kernelMedianUs": 1565969.400,
      "kernelP95Us": 1730976.800,
      "pipeMedianUs": null,
      "dominantStage": "commandApply",
      "vertsTouched": 0
    },
    {
      "name": "remove/vertices/whole",
      "kernelMedianUs": 12954.000,
      "kernelP95Us": 13268.900,
      "pipeMedianUs": null,
      "dominantStage": "commandApply",
      "vertsTouched": 0
    },
    {
      "name": "remove/vertices/half",
      "kernelMedianUs": 1717151.000,
      "kernelP95Us": 1722398.400,
      "pipeMedianUs": null,
      "dominantStage": "commandApply",
      "vertsTouched": 0
    },
    {
      "name": "remove/edges/whole",
      "kernelMedianUs": 62890.800,
      "kernelP95Us": 65282.500,
      "pipeMedianUs": null,
      "dominantStage": "commandApply",
      "vertsTouched": 0
    },
    {
      "name": "remove/polygons/whole",
      "kernelMedianUs": 12344.800,
      "kernelP95Us": 12443.400,
      "pipeMedianUs": null,
      "dominantStage": "commandApply",
      "vertsTouched": 0
    },
    {
      "name": "remove/polygons/half",
      "kernelMedianUs": 1534905.100,
      "kernelP95Us": 1646659.200,
      "pipeMedianUs": null,
      "dominantStage": "commandApply",
      "vertsTouched": 0
    }
  ]
}
